{
 "_type": "song",
 "annotation_count": 5,
 "api_path": "/songs/4359669",
 "artist_names": "Sabrina Carpenter",
 "full_title": "Exhale by\u00a0Sabrina\u00a0Carpenter",
 "header_image_thumbnail_url": "https://images.genius.com/4139890be2d73feee5fb970f11e069d8.300x300x1.png",
 "header_image_url": "https://images.genius.com/4139890be2d73feee5fb970f11e069d8.1000x1000x1.png",
 "id": 4359669,
 "instrumental": false,
 "lyrics_owner_id": 6297057,
 "lyrics_state": "complete",
 "lyrics_updated_at": 1681340583,
 "path": "/Sabrina-carpenter-exhale-lyrics",
 "pyongs_count": 110,
 "relationships_index_url": "https://genius.com/Sabrina-carpenter-exhale-sample",
 "release_date_components": {
  "year": 2019,
  "month": 5,
  "day": 3
 },
 "release_date_for_display": "May 3, 2019",
 "release_date_with_abbreviated_month_for_display": "May. 3, 2019",
 "song_art_image_thumbnail_url": "https://images.genius.com/c4f9d7824539c6e3d872dc9fbd623c70.300x300x1.png",
 "song_art_image_url": "https://images.genius.com/c4f9d7824539c6e3d872dc9fbd623c70.1000x1000x1.png",
 "stats": {
  "unreviewed_annotations": 1,
  "hot": false,
  "pageviews": 90779
 },
 "title": "Exhale",
 "title_with_featured": "Exhale",
 "updated_by_human_at": 1709402404,
 "url": "https://genius.com/Sabrina-carpenter-exhale-lyrics",
 "featured_artists": [],
 "primary_artist": {
  "_type": "artist",
  "api_path": "/artists/249592",
  "header_image_url": "https://images.genius.com/f45a3387ee9cdaebf6638e4e35e3671c.1000x333x1.jpg",
  "id": 249592,
  "image_url": "https://images.genius.com/a9838349411500f7ecb1ebb0d63e06f9.684x684x1.jpg",
  "index_character": "s",
  "is_meme_verified": false,
  "is_verified": true,
  "name": "Sabrina Carpenter",
  "slug": "Sabrina-carpenter",
  "url": "https://genius.com/artists/Sabrina-carpenter",
  "iq": 2075
 },
 "artist": "Sabrina Carpenter",
 "lyrics": "63 ContributorsTranslationsDeutschNederlandsExhale Lyrics\nWho put the baby in charge?\nIt's already hard to buy all the parts and learn to use them\nWho put the world on my back and not in my hands?\nJust give me a chance\n\nListen to my mama, listen to my dad\nListen to my sisters, everyone relax\nEverybody answers shit I didn't ask\nThink I'm reaching my limit\n\nCan I exhale for a minute?\nCan I get this out in the open?\nCan I sit down for a second?\nCan I breathe?\nCan I exhale for a minute?\nCan we talk it out? I don't get it\nCan I calm down for a moment?\nCan I breathe for just one second?\n\nI put too much weight on words and glances\nI, I put too much weight on situations\nI, I put too much on myself\nThinking I don't deserve what I've earned, but yeah\nSee Sabrina Carpenter LiveGet tickets as low as $108You might also like\nI listen to the labels, listen to the man\nTry to keep a sense of knowing who I am\nI try to be an angel, but I don't think I can\nThink I'm reaching my limits, yeah\n\nCan I exhale for a minute?\nCan I get this out in the open?\nCan I sit down for a second?\nCan I breathe?\nCan I exhale for a minute?\nCan we talk it out? I don't get it\nCan I calm down for a moment?\nCan I breathe for just one second, baby?\n\nCan I breathe?\nCan I breathe?\nCan I breathe?\nCan I breathe?\nCan I breathe?\nCan I breathe?\n\nNa na na, na na na, nay\nNa na na, na na na, nay\nNa na na, na na na, nay\nNa na na, na na na, nay\nNa na na, na na na\nNa na na na na na110Embed"
}